a_pandas_ex_less_memory_more_speed/LICENSE
a_pandas_ex_less_memory_more_speed/README.MD
a_pandas_ex_less_memory_more_speed/__init__.py
a_pandas_ex_less_memory_more_speed/requirements.txt
a_pandas_ex_less_memory_more_speed/thirdparty.json
a_pandas_ex_less_memory_more_speed-0.38.dist-info/LICENSE.rst
a_pandas_ex_less_memory_more_speed-0.38.dist-info/METADATA
a_pandas_ex_less_memory_more_speed-0.38.dist-info/WHEEL
a_pandas_ex_less_memory_more_speed-0.38.dist-info/top_level.txt
a_pandas_ex_less_memory_more_speed-0.38.dist-info/RECORD
