Metadata-Version: 2.1
Name: a-pandas-ex-less-memory-more-speed
Version: 0.38
Summary: A Python package to reduce the memory usage of pandas DataFrames. It speeds up your workflow and reduces the risk of running out of memory.
Home-page: https://github.com/hansalemaos/a_pandas_ex_less_memory_more_speed
Author: Johannes Fischer
Author-email: aulasparticularesdealemaosp@gmail.com
License: MIT
Keywords: flatten,pandas,dict,list,numpy,tuple,Tagsiter,nested,iterable,listsoflists,flattenjson,iter,explode,squeeze,nan,pd.NA,np.nan
Classifier: Development Status :: 4 - Beta
Classifier: Programming Language :: Python :: 3 :: Only
Classifier: Programming Language :: Python :: 3.10
Classifier: Topic :: Software Development :: Libraries :: Python Modules
Classifier: Topic :: Utilities
License-File: LICENSE.rst
Requires-Dist: check-if-nan
Requires-Dist: deepcopyall
Requires-Dist: isiter
Requires-Dist: numpy
Requires-Dist: pandas
Requires-Dist: tolerant-isinstance
